Workbook

Sheet SalesData
A1: Order_ID | B1: Order_Date | C1: Month | D1: Region | E1: Salesperson | F1: Category | G1: Product | H1: Quantity | I1: Unit_Price | J1: Discount_% | K1: Revenue | L1: Cost | M1: Profit | N1: Discount Amount | O1: Final Sales | P1: proft %
A2: 1 | B2: 2026-02-27 | C2: =TEXT(Table1[[#This Row],[Order_Date]],"mmm") -> Feb | D2: South | E2: Neha | F2: Office Supplies | G2: Notebook | H2: 1 | I2: 1200 | J2: 5 | K2: =Table1[[#This Row],[Quantity]]*Table1[[#This Row],[Unit_Price]] -> 1200 | L2: 780 | M2: =Table1[[#This Row],[Final Sales]]-Table1[[#This Row],[Cost]] -> 360 | N2: =Table1[[#This Row],[Revenue]]*(Table1[[#This Row],[Discount_%]]/100) -> 60 | O2: =Table1[[#This Row],[Revenue]]-Table1[[#This Row],[Discount Amount]] -> 1140 | P2: =Table1[[#This Row],[Profit]]/Table1[[#This Row],[Final Sales]] -> 0.31578947
A3: 2 | B3: 2026-01-08 | C3: =TEXT(Table1[[#This Row],[Order_Date]],"mmm") -> Jan | D3: North | E3: Riya | F3: Electronics | G3: Laptop | H3: 10 | I3: 5000 | J3: 0 | K3: =Table1[[#This Row],[Quantity]]*Table1[[#This Row],[Unit_Price]] -> 50000 | L3: 32500 | M3: =Table1[[#This Row],[Final Sales]]-Table1[[#This Row],[Cost]] -> 17500 | N3: =Table1[[#This Row],[Revenue]]*(Table1[[#This Row],[Discount_%]]/100) -> 0 | O3: =Table1[[#This Row],[Revenue]]-Table1[[#This Row],[Discount Amount]] -> 50000 | P3: =Table1[[#This Row],[Profit]]/Table1[[#This Row],[Final Sales]] -> 0.35
A4: 3 | B4: 2026-02-26 | C4: =TEXT(Table1[[#This Row],[Order_Date]],"mmm") -> Feb | D4: West | E4: Karan | F4: Electronics | G4: Laptop | H4: 9 | I4: 800 | J4: 15 | K4: =Table1[[#This Row],[Quantity]]*Table1[[#This Row],[Unit_Price]] -> 7200 | L4: 4680 | M4: =Table1[[#This Row],[Final Sales]]-Table1[[#This Row],[Cost]] -> 1440 | N4: =Table1[[#This Row],[Revenue]]*(Table1[[#This Row],[Discount_%]]/100) -> 1080 | O4: =Table1[[#This Row],[Revenue]]-Table1[[#This Row],[Discount Amount]] -> 6120 | P4: =Table1[[#This Row],[Profit]]/Table1[[#This Row],[Final Sales]] -> 0.23529412
A5: 4 | B5: 2026-03-29 | C5: =TEXT(Table1[[#This Row],[Order_Date]],"mmm") -> Mar | D5: East | E5: Riya | F5: Furniture | G5: Chair | H5: 13 | I5: 500 | J5: 15 | K5: =Table1[[#This Row],[Quantity]]*Table1[[#This Row],[Unit_Price]] -> 6500 | L5: 4225 | M5: =Table1[[#This Row],[Final Sales]]-Table1[[#This Row],[Cost]] -> 1300 | N5: =Table1[[#This Row],[Revenue]]*(Table1[[#This Row],[Discount_%]]/100) -> 975 | O5: =Table1[[#This Row],[Revenue]]-Table1[[#This Row],[Discount Amount]] -> 5525 | P5: =Table1[[#This Row],[Profit]]/Table1[[#This Row],[Final Sales]] -> 0.23529412
A6: 5 | B6: 2026-01-25 | C6: =TEXT(Table1[[#This Row],[Order_Date]],"mmm") -> Jan | D6: East | E6: Arjun | F6: Electronics | G6: Keyboard | H6: 2 | I6: 250 | J6: 15 | K6: =Table1[[#This Row],[Quantity]]*Table1[[#This Row],[Unit_Price]] -> 500 | L6: 325 | M6: =Table1[[#This Row],[Final Sales]]-Table1[[#This Row],[Cost]] -> 100 | N6: =Table1[[#This Row],[Revenue]]*(Table1[[#This Row],[Discount_%]]/100) -> 75 | O6: =Table1[[#This Row],[Revenue]]-Table1[[#This Row],[Discount Amount]] -> 425 | P6: =Table1[[#This Row],[Profit]]/Table1[[#This Row],[Final Sales]] -> 0.23529412
A7: 6 | B7: 2026-05-18 | C7: =TEXT(Table1[[#This Row],[Order_Date]],"mmm") -> May | D7: North | E7: Priya | F7: Office Supplies | G7: Marker | H7: 13 | I7: 150 | J7: 15 | K7: =Table1[[#This Row],[Quantity]]*Table1[[#This Row],[Unit_Price]] -> 1950 | L7: 1267.5 | M7: =Table1[[#This Row],[Final Sales]]-Table1[[#This Row],[Cost]] -> 390 | N7: =Table1[[#This Row],[Revenue]]*(Table1[[#This Row],[Discount_%]]/100) -> 292.5 | O7: =Table1[[#This Row],[Revenue]]-Table1[[#This Row],[Discount Amount]] -> 1657.5 | P7: =Table1[[#This Row],[Profit]]/Table1[[#This Row],[Final Sales]] -> 0.23529412
A8: 7 | B8: 2026-01-18 | C8: =TEXT(Table1[[#This Row],[Order_Date]],"mmm") -> Jan | D8: North | E8: Neha | F8: Electronics | G8: Keyboard | H8: 14 | I8: 2500 | J8: 5 | K8: =Table1[[#This Row],[Quantity]]*Table1[[#This Row],[Unit_Price]] -> 35000 | L8: 22750 | M8: =Table1[[#This Row],[Final Sales]]-Table1[[#This Row],[Cost]] -> 10500 | N8: =Table1[[#This Row],[Revenue]]*(Table1[[#This Row],[Discount_%]]/100) -> 1750 | O8: =Table1[[#This Row],[Revenue]]-Table1[[#This Row],[Discount Amount]] -> 33250 | P8: =Table1[[#This Row],[Profit]]/Table1[[#This Row],[Final Sales]] -> 0.31578947
A9: 8 | B9: 2026-04-08 | C9: =TEXT(Table1[[#This Row],[Order_Date]],"mmm") -> Apr | D9: East | E9: Priya | F9: Electronics | G9: Keyboard | H9: 2 | I9: 800 | J9: 0 | K9: =Table1[[#This Row],[Quantity]]*Table1[[#This Row],[Unit_Price]] -> 1600 | L9: 1040 | M9: =Table1[[#This Row],[Final Sales]]-Table1[[#This Row],[Cost]] -> 560 | N9: =Table1[[#This Row],[Revenue]]*(Table1[[#This Row],[Discount_%]]/100) -> 0 | O9: =Table1[[#This Row],[Revenue]]-Table1[[#This Row],[Discount Amount]] -> 1600 | P9: =Table1[[#This Row],[Profit]]/Table1[[#This Row],[Final Sales]] -> 0.35
A10: 9 | B10: 2026-02-23 | C10: =TEXT(Table1[[#This Row],[Order_Date]],"mmm") -> Feb | D10: East | E10: Neha | F10: Office Supplies | G10: Marker | H10: 3 | I10: 2500 | J10: 10 | K10: =Table1[[#This Row],[Quantity]]*Table1[[#This Row],[Unit_Price]] -> 7500 | L10: 4875 | M10: =Table1[[#This Row],[Final Sales]]-Table1[[#This Row],[Cost]] -> 1875 | N10: =Table1[[#This Row],[Revenue]]*(Table1[[#This Row],[Discount_%]]/100) -> 750 | O10: =Table1[[#This Row],[Revenue]]-Table1[[#This Row],[Discount Amount]] -> 6750 | P10: =Table1[[#This Row],[Profit]]/Table1[[#This Row],[Final Sales]] -> 0.27777778
A11: 10 | B11: 2026-02-11 | C11: =TEXT(Table1[[#This Row],[Order_Date]],"mmm") -> Feb | D11: West | E11: Priya | F11: Office Supplies | G11: Notebook | H11: 10 | I11: 500 | J11: 5 | K11: =Table1[[#This Row],[Quantity]]*Table1[[#This Row],[Unit_Price]] -> 5000 | L11: 3250 | M11: =Table1[[#This Row],[Final Sales]]-Table1[[#This Row],[Cost]] -> 1500 | N11: =Table1[[#This Row],[Revenue]]*(Table1[[#This Row],[Discount_%]]/100) -> 250 | O11: =Table1[[#This Row],[Revenue]]-Table1[[#This Row],[Discount Amount]] -> 4750 | P11: =Table1[[#This Row],[Profit]]/Table1[[#This Row],[Final Sales]] -> 0.31578947
A12: 11 | B12: 2026-02-28 | C12: =TEXT(Table1[[#This Row],[Order_Date]],"mmm") -> Feb | D12: North | E12: Arjun | F12: Furniture | G12: Desk | H12: 11 | I12: 2500 | J12: 0 | K12: =Table1[[#This Row],[Quantity]]*Table1[[#This Row],[Unit_Price]] -> 27500 | L12: 17875 | M12: =Table1[[#This Row],[Final Sales]]-Table1[[#This Row],[Cost]] -> 9625 | N12: =Table1[[#This Row],[Revenue]]*(Table1[[#This Row],[Discount_%]]/100) -> 0 | O12: =Table1[[#This Row],[Revenue]]-Table1[[#This Row],[Discount Amount]] -> 27500 | P12: =Table1[[#This Row],[Profit]]/Table1[[#This Row],[Final Sales]] -> 0.35
A13: 12 | B13: 2026-02-24 | C13: =TEXT(Table1[[#This Row],[Order_Date]],"mmm") -> Feb | D13: West | E13: Priya | F13: Furniture | G13: Cabinet | H13: 2 | I13: 800 | J13: 10 | K13: =Table1[[#This Row],[Quantity]]*Table1[[#This Row],[Unit_Price]] -> 1600 | L13: 1040 | M13: =Table1[[#This Row],[Final Sales]]-Table1[[#This Row],[Cost]] -> 400 | N13: =Table1[[#This Row],[Revenue]]*(Table1[[#This Row],[Discount_%]]/100) -> 160 | O13: =Table1[[#This Row],[Revenue]]-Table1[[#This Row],[Discount Amount]] -> 1440 | P13: =Table1[[#This Row],[Profit]]/Table1[[#This Row],[Final Sales]] -> 0.27777778
... A101: 100 | B101: 2026-02-08 | C101: =TEXT(Table1[[#This Row],[Order_Date]],"mmm") -> Feb | D101: South | E101: Karan | F101: Electronics | G101: Monitor | H101: 8 | I101: 250 | J101: 0 | K101: =Table1[[#This Row],[Quantity]]*Table1[[#This Row],[Unit_Price]] -> 2000 | L101: 1300 | M101: =Table1[[#This Row],[Final Sales]]-Table1[[#This Row],[Cost]] -> 700 | N101: =Table1[[#This Row],[Revenue]]*(Table1[[#This Row],[Discount_%]]/100) -> 0 | O101: =Table1[[#This Row],[Revenue]]-Table1[[#This Row],[Discount Amount]] -> 2000 | P101: =Table1[[#This Row],[Profit]]/Table1[[#This Row],[Final Sales]] -> 0.35

Sheet Pivot
B2: Month | C2: Sum of Final Sales | H2: Product | I2: Sum of Profit
B3: Jan | C3: 537890 | H3: Cabinet | I3: 78060
B4: Feb | C4: 198992.5 | E4: Category | F4: Sum of Profit | H4: Chair | I4: 31082.5
B5: Mar | C5: 157450 | E5: Furniture | F5: 199265 | H5: Desk | I5: 80090
B6: Apr | C6: 629467.5 | E6: Grand Total | F6: 199265 | H6: Keyboard | I6: 31460
B7: May | C7: 296672.5 | H7: Laptop | I7: 94820
B8: Jun | C8: 134825 | H8: Marker | I8: 95952.5
B9: (blank) | H9: Monitor | I9: 17900
B10: Grand Total | C10: 1955297.5 | H10: Mouse | I10: 26700
H11: Notebook | I11: 50722.5
E12: Region | F12: Sum of Final Sales | H12: Pen | I12: 21190
B13: Salesperson | C13: Sum of Profit | E13: East | F13: 586827.5 | H13: Stapler | I13: 44520
B14: Anmol | C14: 47742.5 | E14: North | F14: 345482.5 | H14: Table | I14: 10032.5
B15: Arjun | C15: 143195 | E15: South | F15: 617795 | H15: Grand Total | I15: 582530
B16: Karan | C16: 49460 | E16: West | F16: 405192.5
B17: Neha | C17: 128120 | E17: Grand Total | F17: 1955297.5
B18: Priya | C18: 83080
B19: Riya | C19: 130932.5
B20: Grand Total | C20: 582530

Sheet Dashboard
A1: EXCEL SALES & PERFORMANCE DASHBOARD
A4: Management Overview | 2024–2026
A6: Total Revenue | C6: Total Profit | E6: Total Orders | G6: Avg Order Values | I6: Avg Discount
A7: =SUM(SalesData!O:O) -> 1955297.5 | C7: =SUM(SalesData!M:M) -> 582530 | E7: =COUNTA(SalesData!A:A) -> 101 | G7: =AVERAGE(SalesData!O:O) -> 19552.975 | I7: =AVERAGE(SalesData!J:J)/100 -> 0.0765
